[
  {
    "description": "    Application Regression",
    "keyword": "Feature",
    "name": "End to End Ecommerce Validation",
    "line": 1,
    "id": "end-to-end-ecommerce-validation",
    "tags": [],
    "uri": "ecommerce.feature",
    "elements": [
      {
        "id": "end-to-end-ecommerce-validation;ecommerce-products-delivery",
        "keyword": "Scenario",
        "line": 8,
        "name": "Ecommerce products delivery",
        "tags": [],
        "type": "scenario",
        "steps": [
          {
            "arguments": [],
            "keyword": "Given ",
            "line": 6,
            "name": "Angluar Practice page has been launched",
            "result": {
              "status": "passed",
              "duration": 1713000000
            }
          },
          {
            "arguments": [],
            "keyword": "Given ",
            "line": 9,
            "name": "I open ecommerce page",
            "result": {
              "status": "passed",
              "duration": 2024000000
            }
          },
          {
            "arguments": [],
            "keyword": "When ",
            "line": 10,
            "name": "I add items to Cart",
            "result": {
              "status": "passed",
              "duration": 962000000
            }
          },
          {
            "arguments": [],
            "keyword": "Then ",
            "line": 11,
            "name": "Select the country submit",
            "result": {
              "status": "passed",
              "duration": 1069000000
            }
          },
          {
            "arguments": [],
            "keyword": "And ",
            "line": 12,
            "name": "Validate thankyou message",
            "result": {
              "status": "passed",
              "duration": 100000000
            }
          }
        ]
      }
    ]
  }
]